LICENSE
MANIFEST.in
README.md
helga_flip.py
setup.py
helga_flip.egg-info/PKG-INFO
helga_flip.egg-info/SOURCES.txt
helga_flip.egg-info/dependency_links.txt
helga_flip.egg-info/entry_points.txt
helga_flip.egg-info/top_level.txt