Metadata-Version: 1.1
Name: helga-flip
Version: 0.1.0
Summary: Helga plugin to flip words
Home-page: https://github.com/shaunduncan/helga-flip
Author: Shaun Duncan
Author-email: shaun.duncan@gmail.com
License: GPLv3
Keywords: helga flip
Platform: UNKNOWN
Classifier: Development Status :: 4 - Beta
Classifier: Topic :: Communications :: Chat :: Internet Relay Chat
Classifier: Framework :: Twisted
Classifier: License :: OSI Approved :: GNU General Public License v3 (GPLv3)
Classifier: Operating System :: OS Independent
Classifier: Programming Language :: Python
Classifier: Programming Language :: Python :: 2
Classifier: Programming Language :: Python :: 2.6
Classifier: Programming Language :: Python :: 2.7
Classifier: Topic :: Software Development :: Libraries :: Python Modules
